code_compass/__init__.py
code_compass/app.py
code_compass/category.py
code_compass/config.py
code_compass/config.yaml
code_compass/db.py
code_compass/project.py
code_compass/~/.config/charm_runner/data.db
code_compass-0.1.2.dist-info/entry_points.txt
code_compass-0.1.2.dist-info/WHEEL
code_compass-0.1.2.dist-info/METADATA
code_compass-0.1.2.dist-info/RECORD
