Metadata-Version: 2.1
Name: code-compass
Version: 0.1.2
Summary: 
Author: Roman
Author-email: roman-right@protonmail.com
Requires-Python: >=3.10,<3.12
Classifier: Programming Language :: Python :: 3
Classifier: Programming Language :: Python :: 3.10
Classifier: Programming Language :: Python :: 3.11
Requires-Dist: cookiecutter (>=2.1.1,<3.0.0)
Requires-Dist: pyside6 (>=6.5.0,<7.0.0)
